pyclavis/__init__.py
pyclavis/__main__.py
pyclavis/backend.py
pyclavis/bgtask.py
pyclavis/browse.py
pyclavis/common.py
pyclavis/config.py
pyclavis/const.py
pyclavis/conv.py
pyclavis/credit.py
pyclavis/downloads.py
pyclavis/favorites.py
pyclavis/gui.py
pyclavis/icons.py
pyclavis/keyconv.py
pyclavis/logging.py
pyclavis/loginproc.py
pyclavis/main.py
pyclavis/passgen.py
pyclavis/profiles.py
pyclavis/pyclavis.py
pyclavis/replacer.py
pyclavis/singleinstance.py
pyclavis/store.py
pyclavis/updatecheck.py
pyclavis/xgui_util.py
pyclavis/tile/__init__.py
pyclavis/tile/core.py
pyclavis/tile/tkcmd.py
pyclavis-0.0.9.dist-info/LICENSE.md
pyclavis-0.0.9.dist-info/METADATA
pyclavis-0.0.9.dist-info/WHEEL
pyclavis-0.0.9.dist-info/entry_points.txt
pyclavis-0.0.9.dist-info/top_level.txt
pyclavis-0.0.9.dist-info/RECORD
