Metadata-Version: 2.1
Name: pyclavis
Version: 0.0.9
Summary: pyclavis key-store password manager with autofill templates as predefined download
Home-page: https://github.com/kr-g/pyclavis
Author: k. goger
Author-email: k.r.goger+pyclavis@gmail.com
License: AGPLv3+
Project-URL: Issues, https://github.com/kr-g/pyclavis/issues
Keywords: python utility shell git password-manager key-store
Platform: UNKNOWN
Classifier: Development Status :: 3 - Alpha
Classifier: Operating System :: POSIX :: Linux
Classifier: Environment :: Console
Classifier: Environment :: Other Environment
Classifier: Intended Audience :: Developers
Classifier: Intended Audience :: System Administrators
Classifier: Intended Audience :: End Users/Desktop
Classifier: Topic :: Utilities
Classifier: Topic :: Desktop Environment
Classifier: Topic :: Internet
Classifier: Topic :: Home Automation
Classifier: Topic :: Office/Business
Classifier: Topic :: Security
Classifier: Topic :: Security :: Cryptography
Classifier: Programming Language :: Python :: 3
Classifier: License :: Free For Home Use
Classifier: License :: Free for non-commercial use
Classifier: License :: Free To Use But Restricted
Classifier: License :: Other/Proprietary License
Classifier: License :: OSI Approved :: GNU Affero General Public License v3 or later (AGPLv3+)
Requires-Python: >=3.10
License-File: LICENSE.md
Requires-Dist: cryptography
Requires-Dist: pyautogui
Requires-Dist: pygitgrab
Requires-Dist: pyjsoncfg
Requires-Dist: pyperclip
Requires-Dist: pytkfaicons
Requires-Dist: semver
Requires-Dist: tkinter-tooltip
